arcae/__init__.py
arcae/config.py
arcae/testing.py
arcae/applications/__init__.py
arcae/applications/entrypoint.py
arcae/applications/ms_export.py
arcae/lib/arrow_tables.cpython-313-x86_64-linux-gnu.so
arcae/lib/libarcae.so
arcae/tests/__init__.py
arcae/tests/conftest.py
arcae/tests/test_casting.py
arcae/tests/test_descriptor.py
arcae/tests/test_multithreaded_read.py
arcae/tests/test_partition_sort.py
arcae/tests/test_pytable.py
arcae.libs/libcasa_casa-3a39977b.so.8
arcae.libs/libcasa_coordinates-cc4165bc.so.8
arcae.libs/libcasa_derivedmscal-067edfd8.so.8
arcae.libs/libcasa_fits-a8186ae4.so.8
arcae.libs/libcasa_images-2d0ef494.so.8
arcae.libs/libcasa_lattices-0eefe06a.so.8
arcae.libs/libcasa_meas-7988ee1d.so.8
arcae.libs/libcasa_measures-662e51fb.so.8
arcae.libs/libcasa_mirlib-dc3d529c.so.8
arcae.libs/libcasa_ms-cac4d845.so.8
arcae.libs/libcasa_msfits-c5280e98.so.8
arcae.libs/libcasa_scimath-ad5e2bd7.so.8
arcae.libs/libcasa_scimath_f-9a515e54.so.8
arcae.libs/libcasa_tables-d2cad6f5.so.8
arcae.libs/libcfitsio-112984df.so.4.1.0
arcae.libs/libgfortran-83c28eba.so.5.0.0
arcae.libs/libgsl-1ae49399.so
arcae.libs/libgslcblas-17e5d48c.so
arcae.libs/liblapack-10665d0a.so.3.12.0
arcae.libs/libopenblas-635eee5f.so.0.3
arcae.libs/libquadmath-2284e583.so.0.0.0
arcae.libs/libwcs-617ce2a1.so.8.3
arcae-0.3.3.dist-info/METADATA
arcae-0.3.3.dist-info/WHEEL
arcae-0.3.3.dist-info/entry_points.txt
arcae-0.3.3.dist-info/RECORD
arcae-0.3.3.dist-info/licenses/LICENSE
