Metadata-Version: 2.2
Name: arcae
Version: 0.3.3
Summary: Arrow bindings for casacore
Author-Email: Simon Perkins <simon.perkins@gmail.com>
License: BSD 3-Clause License
Classifier: License :: OSI Approved :: BSD License
Classifier: Programming Language :: Python :: 3
Project-URL: Repository, https://github.com/ratt-ru/arcae
Requires-Python: >=3.11
Requires-Dist: numpy>=2.0.0
Requires-Dist: pyarrow==22.0.0
Provides-Extra: applications
Requires-Dist: click; extra == "applications"
Requires-Dist: rich; extra == "applications"
Provides-Extra: dev
Requires-Dist: pre-commit; extra == "dev"
Requires-Dist: tbump; extra == "dev"
Provides-Extra: test
Requires-Dist: duckdb; extra == "test"
Requires-Dist: platformdirs; extra == "test"
Requires-Dist: pytest>=7.0.0; extra == "test"
Requires-Dist: python-casacore>=3.5.0; sys_platform == "linux" and platform_machine == "x86_64" and python_version < "3.14" and extra == "test"
Requires-Dist: requests; extra == "test"
